setup.py
ujwal_test_package/Binomialdistribution.py
ujwal_test_package/Gaussiandistribution.py
ujwal_test_package/Generaldistribution.py
ujwal_test_package/__init__.py
ujwal_test_package.egg-info/PKG-INFO
ujwal_test_package.egg-info/SOURCES.txt
ujwal_test_package.egg-info/dependency_links.txt
ujwal_test_package.egg-info/not-zip-safe
ujwal_test_package.egg-info/top_level.txt