Metadata-Version: 1.0
Name: ujwal-test-package
Version: 0.1
Summary: Gaussian distributions
Home-page: UNKNOWN
Author: UNKNOWN
Author-email: ujwal98@gmail.com
License: UNKNOWN
Platform: UNKNOWN
